newold/__init__.py
newold/__main__.py
newold/version.py
newold-0.0.2.dist-info/LICENSE
newold-0.0.2.dist-info/METADATA
newold-0.0.2.dist-info/WHEEL
newold-0.0.2.dist-info/entry_points.txt
newold-0.0.2.dist-info/top_level.txt
newold-0.0.2.dist-info/RECORD
