Metadata-Version: 2.1
Name: newold
Version: 0.0.2
Summary: Print only new values to stdout, or those that weren't seen in a while.
Home-page: https://gitlab.com/Zer1t0/newold
Author: Eloy Pérez González
Classifier: Programming Language :: Python :: 3
Classifier: License :: OSI Approved :: GNU General Public License v3 (GPLv3)
License-File: LICENSE
Requires-Dist: tomlkit
